icechunk-1.1.15.dist-info/METADATA
icechunk-1.1.15.dist-info/WHEEL
icechunk-1.1.15.dist-info/entry_points.txt
icechunk-1.1.15.dist-info/licenses/LICENSE
icechunk/__init__.py
icechunk/_icechunk_python.cpython-314-darwin.so
icechunk/_icechunk_python.pyi
icechunk/credentials.py
icechunk/dask.py
icechunk/distributed.py
icechunk/py.typed
icechunk/repository.py
icechunk/session.py
icechunk/storage.py
icechunk/store.py
icechunk/testing/strategies.py
icechunk/vendor/__init__.py
icechunk/vendor/xarray.py
icechunk/xarray.py
icechunk-1.1.15.dist-info/RECORD
