Metadata-Version: 2.4
Name: icechunk
Version: 1.1.15
Classifier: Programming Language :: Rust
Classifier: Programming Language :: Python :: Implementation :: CPython
Classifier: Programming Language :: Python :: Implementation :: PyPy
Classifier: Programming Language :: Python :: 3
Classifier: Programming Language :: Python :: 3.11
Classifier: Programming Language :: Python :: 3.12
Classifier: Programming Language :: Python :: 3.13
Classifier: Programming Language :: Python :: 3.14
Requires-Dist: zarr>=3,!=3.0.3
Requires-Dist: boto3 ; extra == 'test'
Requires-Dist: coverage ; extra == 'test'
Requires-Dist: mypy ; extra == 'test'
Requires-Dist: object-store-python ; extra == 'test'
Requires-Dist: pytest ; extra == 'test'
Requires-Dist: pytest-cov ; extra == 'test'
Requires-Dist: pytest-asyncio ; extra == 'test'
Requires-Dist: pytest-xdist ; extra == 'test'
Requires-Dist: ruff ; extra == 'test'
Requires-Dist: dask>=2024.11.0 ; extra == 'test'
Requires-Dist: distributed>=2024.11.0 ; extra == 'test'
Requires-Dist: xarray>=2025.1.2 ; extra == 'test'
Requires-Dist: hypothesis ; extra == 'test'
Requires-Dist: pandas-stubs ; extra == 'test'
Requires-Dist: boto3-stubs[s3] ; extra == 'test'
Requires-Dist: termcolor ; extra == 'test'
Requires-Dist: pooch ; extra == 'test'
Requires-Dist: netcdf4 ; extra == 'test'
Requires-Dist: pytest-benchmark[histogram] ; extra == 'benchmark'
Requires-Dist: pytest-xdist ; extra == 'benchmark'
Requires-Dist: s3fs ; extra == 'benchmark'
Requires-Dist: gcsfs ; extra == 'benchmark'
Requires-Dist: h5netcdf ; extra == 'benchmark'
Requires-Dist: pooch ; extra == 'benchmark'
Requires-Dist: tqdm ; extra == 'benchmark'
Requires-Dist: humanize ; extra == 'benchmark'
Requires-Dist: platformdirs ; extra == 'benchmark'
Requires-Dist: ipdb ; extra == 'benchmark'
Requires-Dist: coiled ; extra == 'benchmark'
Requires-Dist: scipy ; extra == 'docs'
Requires-Dist: cftime ; extra == 'docs'
Requires-Dist: pooch ; extra == 'docs'
Requires-Dist: dask>=2024.11.0 ; extra == 'docs'
Requires-Dist: distributed>=2024.11.0 ; extra == 'docs'
Requires-Dist: xarray>=2025.1.2 ; extra == 'docs'
Requires-Dist: myst-nb ; extra == 'docs'
Requires-Dist: pydata-sphinx-theme ; extra == 'docs'
Requires-Dist: mkdocs-awesome-pages-plugin ; extra == 'docs'
Requires-Dist: mkdocs-mermaid2-plugin ; extra == 'docs'
Requires-Dist: markdown-exec ; extra == 'docs'
Requires-Dist: mkdocs-breadcrumbs-plugin ; extra == 'docs'
Requires-Dist: mkdocs-minify-plugin ; extra == 'docs'
Requires-Dist: mkdocs-open-in-new-tab ; extra == 'docs'
Requires-Dist: mkdocs ; extra == 'docs'
Requires-Dist: mkdocs-material[imaging] ; extra == 'docs'
Requires-Dist: mkdocstrings[python] ; extra == 'docs'
Requires-Dist: mkdocs-jupyter ; extra == 'docs'
Requires-Dist: mkdocs-git-revision-date-localized-plugin ; extra == 'docs'
Requires-Dist: mkdocs-git-committers-plugin-2 ; extra == 'docs'
Requires-Dist: mkdocs-macros-plugin ; extra == 'docs'
Requires-Dist: mkdocs-include-markdown-plugin ; extra == 'docs'
Requires-Dist: mkdocs-redirects ; extra == 'docs'
Requires-Dist: mkdocs-git-authors-plugin ; extra == 'docs'
Requires-Dist: sphinx ; extra == 'docs'
Requires-Dist: sphinx-copybutton ; extra == 'docs'
Requires-Dist: sphinx-design ; extra == 'docs'
Requires-Dist: sphinx-togglebutton ; extra == 'docs'
Requires-Dist: sphinx-autodoc-typehints ; extra == 'docs'
Provides-Extra: test
Provides-Extra: benchmark
Provides-Extra: docs
License-File: LICENSE
Summary: Icechunk Python
Home-Page: https://icechunk.io
Author-email: Earthmover <info@earthmover.io>
Requires-Python: >=3.11
